{
  "posts": [
    {
      "id": 1,
      "title": "json-server",
      "author": "typicode"
    }
  ],
  "comments": [
    {
      "id": 1,
      "body": "some comment",
      "postId": 1
    }
  ],



  "place": [
    {
      "id": "8201",
      "name": "KEMZ",
      "apiId": "v1"
    },
    {
      "id": "8203",
      "name": "ELESI",
      "apiId": "v1",
      "devices": [
        {
          "id": "11:11:11",
          "type": "light",
          "name": "a",
          "place": "8203"
        }
      ]
    },
    {
      "id": "8103",
      "name": "FirstFloor",
      "apiId": "v1"
    },
    {
      "name": "TestRoom",
      "id": "1000",
      "apiId": "v1"
    }
  ],
  "login": {
    "username": "trheh",
    "password": "1",
    "apiId": "v1"
  }
}